Metadata-Version: 2.1
Name: drf-multiple-serializer
Version: 0.2.3
Summary: Django REST framework serializer utility
Home-page: https://github.com/qpfmtlcp/drf-multiple-serializer
Author: jay kim
Author-email: jaykim1361@gmail.com
License: MIT
Keywords: django,drf,serializer
Platform: UNKNOWN
Classifier: Development Status :: 4 - Beta
Classifier: Intended Audience :: Developers
Classifier: License :: OSI Approved :: MIT License
Classifier: Environment :: Web Environment
Classifier: Framework :: Django
Classifier: Programming Language :: Python :: 3
Requires-Python: >=3
